ecleankernel/__init__.py
ecleankernel/__main__.py
ecleankernel/file.py
ecleankernel/kernel.py
ecleankernel/process.py
ecleankernel/sort.py
ecleankernel/bootloader/__init__.py
ecleankernel/bootloader/grub.py
ecleankernel/bootloader/grub2.py
ecleankernel/bootloader/lilo.py
ecleankernel/bootloader/symlinks.py
ecleankernel/bootloader/yaboot.py
ecleankernel/layout/__init__.py
ecleankernel/layout/blspec.py
ecleankernel/layout/moduledir.py
ecleankernel/layout/std.py
eclean_kernel-2.99.10.dist-info/entry_points.txt
eclean_kernel-2.99.10.dist-info/COPYING
eclean_kernel-2.99.10.dist-info/WHEEL
eclean_kernel-2.99.10.dist-info/METADATA
eclean_kernel-2.99.10.dist-info/RECORD
