Metadata-Version: 2.3
Name: eclean-kernel
Version: 2.99.10
Summary: Installed kernel cleanup tool
Author-email: Michał Górny <mgorny@gentoo.org>
Requires-Python: >=3.9
Classifier: Development Status :: 4 - Beta
Classifier: Environment :: Console
Classifier: Intended Audience :: System Administrators
Classifier: License :: OSI Approved :: GNU General Public License v2 or later (GPLv2+)
Classifier: Operating System :: POSIX
Classifier: Programming Language :: Python :: 3 :: Only
Classifier: Topic :: System :: Installation/Setup
Requires-Dist: distro
Requires-Dist: pytest ; extra == "test"
Project-URL: Homepage, https://github.com/projg2/eclean-kernel/
Provides-Extra: test
